README.txt
setup.cfg
setup.py
cQuery.egg-info/PKG-INFO
cQuery.egg-info/SOURCES.txt
cQuery.egg-info/dependency_links.txt
cQuery.egg-info/entry_points.txt
cQuery.egg-info/not-zip-safe
cQuery.egg-info/top_level.txt
cquery/__init__.py
cquery/__main__.py
cquery/cli.py
cquery/lib.py
cquery/version.py
cquery/tests/__init__.py
cquery/tests/test_reading.py
cquery/tests/test_writing.py
cquery/vendor/__init__.py
cquery/vendor/click/__init__.py
cquery/vendor/click/_bashcomplete.py
cquery/vendor/click/_compat.py
cquery/vendor/click/_termui_impl.py
cquery/vendor/click/_textwrap.py
cquery/vendor/click/core.py
cquery/vendor/click/decorators.py
cquery/vendor/click/exceptions.py
cquery/vendor/click/formatting.py
cquery/vendor/click/parser.py
cquery/vendor/click/termui.py
cquery/vendor/click/testing.py
cquery/vendor/click/types.py
cquery/vendor/click/utils.py
cquery/vendor/nose/__init__.py
cquery/vendor/nose/__main__.py
cquery/vendor/nose/case.py
cquery/vendor/nose/commands.py
cquery/vendor/nose/config.py
cquery/vendor/nose/core.py
cquery/vendor/nose/exc.py
cquery/vendor/nose/failure.py
cquery/vendor/nose/importer.py
cquery/vendor/nose/inspector.py
cquery/vendor/nose/loader.py
cquery/vendor/nose/proxy.py
cquery/vendor/nose/pyversion.py
cquery/vendor/nose/result.py
cquery/vendor/nose/selector.py
cquery/vendor/nose/suite.py
cquery/vendor/nose/twistedtools.py
cquery/vendor/nose/util.py
cquery/vendor/nose/ext/__init__.py
cquery/vendor/nose/ext/dtcompat.py
cquery/vendor/nose/plugins/__init__.py
cquery/vendor/nose/plugins/allmodules.py
cquery/vendor/nose/plugins/attrib.py
cquery/vendor/nose/plugins/base.py
cquery/vendor/nose/plugins/builtin.py
cquery/vendor/nose/plugins/capture.py
cquery/vendor/nose/plugins/collect.py
cquery/vendor/nose/plugins/cover.py
cquery/vendor/nose/plugins/debug.py
cquery/vendor/nose/plugins/deprecated.py
cquery/vendor/nose/plugins/doctests.py
cquery/vendor/nose/plugins/errorclass.py
cquery/vendor/nose/plugins/failuredetail.py
cquery/vendor/nose/plugins/isolate.py
cquery/vendor/nose/plugins/logcapture.py
cquery/vendor/nose/plugins/manager.py
cquery/vendor/nose/plugins/multiprocess.py
cquery/vendor/nose/plugins/plugintest.py
