Metadata-Version: 1.1
Name: cQuery
Version: 0.2.1
Summary: Decentralised content queries
Home-page: https://github.com/abstractfactory/cquery
Author: Marcus Ottosson
Author-email: marcus@abstractfactory.com
License: license.txt
Platform: UNKNOWN
Classifier: Development Status :: 3 - Alpha
Classifier: Intended Audience :: Developers
Classifier: License :: OSI Approved :: GNU Lesser General Public License v3 (LGPLv3)
Classifier: Programming Language :: Python
Classifier: Programming Language :: Python :: 2
Classifier: Programming Language :: Python :: 2.6
Classifier: Programming Language :: Python :: 2.7
Classifier: Topic :: Software Development :: Libraries :: Python Modules
Classifier: Topic :: Utilities
